README.rst
boltzmannclean.py
setup.py
sherlockml_boltzmannclean.egg-info/PKG-INFO
sherlockml_boltzmannclean.egg-info/SOURCES.txt
sherlockml_boltzmannclean.egg-info/dependency_links.txt
sherlockml_boltzmannclean.egg-info/requires.txt
sherlockml_boltzmannclean.egg-info/top_level.txt