Metadata-Version: 1.0
Name: sherlockml-boltzmannclean
Version: 0.1.2
Summary: Fills missing values in a pandas DataFrame using a Restricted Boltzmann Machine.
Home-page: https://sherlockml.com
Author: ASI Data Science
Author-email: engineering@asidatascience.com
License: Apache 2.0
Platform: UNKNOWN
